momoposter/__init__.py
momoposter/momoposter.py
momoposter/poster.py
momoposter-0.0.8.dist-info/METADATA
momoposter-0.0.8.dist-info/WHEEL
momoposter-0.0.8.dist-info/top_level.txt
momoposter-0.0.8.dist-info/RECORD
