Metadata-Version: 2.1
Name: momoposter
Version: 0.0.8
Summary: Backlink Builder
Author: Momo Poster
Author-email: <momo@cleardex.io>
Keywords: python,backlink builder,seo,poster,link builder,momoposter
Classifier: Development Status :: 3 - Alpha
Classifier: Intended Audience :: Education
Classifier: Programming Language :: Python :: 2
Classifier: Programming Language :: Python :: 3
Classifier: Operating System :: MacOS :: MacOS X
Classifier: Operating System :: Microsoft :: Windows
Requires-Dist: telegraph
Requires-Dist: spintax
